{
  "_fv": 24,
  "_type": "recipe",
  "definition": {
    "recipeType": "Crafting",
    "xpReward": 0.0,
    "cookingTime": 200,
    "recipeRetstackSize": 1,
    "group": "elec_tronics",
    "recipeShapeless": false,
    "recipeSlots": [
      {
        "value": ""
      },
      {
        "value": "Items.IRON_INGOT"
      },
      {
        "value": ""
      },
      {
        "value": "CUSTOM:Sharpenediron"
      },
      {
        "value": "CUSTOM:Irongear"
      },
      {
        "value": "CUSTOM:Sharpenediron"
      },
      {
        "value": ""
      },
      {
        "value": "Items.IRON_INGOT"
      },
      {
        "value": ""
      }
    ],
    "recipeReturnStack": {
      "value": "CUSTOM:Turbine"
    },
    "name": "turbinerecipe",
    "namespace": "mod"
  }
}